archetypes/__init__.py
archetypes/datasets/__init__.py
archetypes/datasets/_make_archetypal_dataset.py
archetypes/numpy/__init__.py
archetypes/numpy/_aa.py
archetypes/numpy/_ada.py
archetypes/numpy/_biaa.py
archetypes/numpy/_fair_aa.py
archetypes/numpy/_fair_kernel_aa.py
archetypes/numpy/_inits.py
archetypes/numpy/_kernel_aa.py
archetypes/numpy/_naa.py
archetypes/numpy/_projection.pyx
archetypes/numpy/_sym_biaa.py
archetypes/processing/__init__.py
archetypes/processing/_closest.py
archetypes/processing/_permute.py
archetypes/processing/_sort.py
archetypes/utils/__init__.py
archetypes/utils/check_generator.py
archetypes/utils/utils.py
archetypes/visualization/__init__.py
archetypes/visualization/bisimplex.py
archetypes/visualization/circular_bar.py
archetypes/visualization/heatmap.py
archetypes/visualization/network.py
archetypes/visualization/simplex.py
archetypes/visualization/stacked_bar.py
archetypes/visualization/utils.py
archetypes/numpy/_projection.cpython-39-darwin.so
archetypes-0.11.1.dist-info/METADATA
archetypes-0.11.1.dist-info/WHEEL
archetypes-0.11.1.dist-info/licenses/LICENSE
archetypes-0.11.1.dist-info/RECORD
