Metadata-Version: 2.4
Name: archetypes
Version: 0.11.1
Summary: A scikit-learn compatible Python package for archetypal analysis
Project-URL: Documentation, https://archetypes.readthedocs.io
Project-URL: Source code, https://github.com/aleixalcacer/archetypes
Author-email: Aleix Alcacer <aleixalcacer@gmail.com>, Zanchenling Wang <wangzancl@gmail.com>
License-Expression: BSD-3-Clause
License-File: LICENSE
Classifier: Development Status :: 4 - Beta
Classifier: Intended Audience :: Developers
Classifier: Intended Audience :: Science/Research
Classifier: Natural Language :: English
Classifier: Operating System :: OS Independent
Classifier: Programming Language :: Python
Classifier: Programming Language :: Python :: 3.9
Classifier: Programming Language :: Python :: 3.10
Classifier: Programming Language :: Python :: 3.11
Classifier: Programming Language :: Python :: 3.12
Classifier: Programming Language :: Python :: Implementation :: CPython
Classifier: Topic :: Scientific/Engineering
Requires-Python: >=3.9
Requires-Dist: matplotlib>=3.8
Requires-Dist: numpy>=1.25
Requires-Dist: opt-einsum
Requires-Dist: pykronecker
Requires-Dist: scikit-learn>=1.6
Requires-Dist: scipy<1.12,>=1.8; python_version < '3.11'
Requires-Dist: scipy>=1.16; python_version >= '3.11'
